{
  "schema_version": "1.0.0",
  "generated_at": "2026-05-06T06:16:40.912601+00:00",
  "generated_at_utc": "2026-05-06T06:16:40.912619+00:00",
  "summary": {
    "total_articles": 30,
    "overall_sentiment": "neutral",
    "sentiment_breakdown": {
      "positive": 20.0,
      "neutral": 63.3,
      "negative": 16.7
    },
    "breaking_news_count": 3
  },
  "trends": {
    "overall_sentiment": "neutral",
    "sentiment_counts": {
      "positive": 6,
      "neutral": 19,
      "negative": 5
    },
    "sentiment_percentages": {
      "positive": 20.0,
      "neutral": 63.3,
      "negative": 16.7
    },
    "category_counts": {
      "financial": 15,
      "crypto": 10,
      "general": 5
    },
    "breaking_news": [
      {
        "title": "Michael Burry sells entire stake in surging meme-stock giant",
        "source": "Yahoo Finance",
        "sentiment": "neutral",
        "impact": 100
      },
      {
        "title": "Alarm bells raised over fintech firm\u2019s bank purchase",
        "source": "Yahoo Finance",
        "sentiment": "negative",
        "impact": 100
      },
      {
        "title": "Jim Cramer on Cloudflare: \u201cThey\u2019re a Terrific Cyber Defender\u201d",
        "source": "Yahoo Finance",
        "sentiment": "neutral",
        "impact": 100
      }
    ]
  },
  "top_articles": [
    {
      "title": "Michael Burry sells entire stake in surging meme-stock giant",
      "summary": "",
      "link": "https://finance.yahoo.com/markets/stocks/articles/michael-burry-sells-entire-stake-202300350.html",
      "source": "Yahoo Finance",
      "category": "financial",
      "sentiment": "neutral",
      "impact_score": 100,
      "timestamp": "2026-05-06T06:16:36.425242+00:00",
      "published": "2026-05-05T20:23:00Z"
    },
    {
      "title": "Alarm bells raised over fintech firm\u2019s bank purchase",
      "summary": "",
      "link": "https://finance.yahoo.com/economy/policy/articles/alarm-bells-raised-over-fintech-030700036.html",
      "source": "Yahoo Finance",
      "category": "financial",
      "sentiment": "negative",
      "impact_score": 100,
      "timestamp": "2026-05-06T06:16:36.425291+00:00",
      "published": "2026-05-05T03:07:00Z"
    },
    {
      "title": "Jim Cramer on Cloudflare: \u201cThey\u2019re a Terrific Cyber Defender\u201d",
      "summary": "",
      "link": "https://finance.yahoo.com/markets/stocks/articles/jim-cramer-cloudflare-terrific-cyber-184731835.html",
      "source": "Yahoo Finance",
      "category": "financial",
      "sentiment": "neutral",
      "impact_score": 100,
      "timestamp": "2026-05-06T06:16:36.425318+00:00",
      "published": "2026-05-04T18:47:31Z"
    },
    {
      "title": "Jim Cramer Explains Why Berkshire Hathaway \u201cUnderperformed of Late\u201d",
      "summary": "",
      "link": "https://finance.yahoo.com/markets/stocks/articles/jim-cramer-explains-why-berkshire-184733352.html",
      "source": "Yahoo Finance",
      "category": "financial",
      "sentiment": "neutral",
      "impact_score": 100,
      "timestamp": "2026-05-06T06:16:36.425341+00:00",
      "published": "2026-05-04T18:47:33Z"
    },
    {
      "title": "Jim Cramer on Merck & Co.: \u201cThe Stock\u2019s Starting to Come Back\u201d",
      "summary": "",
      "link": "https://finance.yahoo.com/markets/stocks/articles/jim-cramer-merck-co-stock-184817086.html",
      "source": "Yahoo Finance",
      "category": "financial",
      "sentiment": "neutral",
      "impact_score": 100,
      "timestamp": "2026-05-06T06:16:36.425359+00:00",
      "published": "2026-05-04T18:48:17Z"
    },
    {
      "title": "Oil futures fall after Trump pauses U.S. effort to partially reopen Strait of Hormuz",
      "summary": "Crude-oil futures fell late Tuesday after President Donald Trump said his latest effort to partially reopen the Strait of Hormuz would be paused, to buy more time to reach an agreement to end hostilities with Iran.",
      "link": "https://www.marketwatch.com/story/oil-futures-fall-after-trump-pauses-u-s-effort-to-partially-reopen-strait-of-hormuz-936c77f9?mod=mw_rss_topstories",
      "source": "MarketWatch Top Stories",
      "category": "financial",
      "sentiment": "negative",
      "impact_score": 100,
      "timestamp": "2026-05-06T06:16:39.835127+00:00",
      "published": "Wed, 06 May 2026 02:22:00 GMT"
    },
    {
      "title": "Astera Labs\u2019 stock climbs as the company strives to make AI chips more powerful",
      "summary": "The connectivity company also issued upbeat earnings results",
      "link": "https://www.marketwatch.com/story/astera-labs-stock-climbs-as-the-company-strives-to-make-ai-chips-more-powerful-2c9be4d6?mod=mw_rss_topstories",
      "source": "MarketWatch Top Stories",
      "category": "financial",
      "sentiment": "neutral",
      "impact_score": 100,
      "timestamp": "2026-05-06T06:16:39.835182+00:00",
      "published": "Wed, 06 May 2026 00:32:00 GMT"
    },
    {
      "title": "Super Micro\u2019s stock surges as Wall Street cheers its margin recovery",
      "summary": "Shares of the AI server maker jumped 18% as investors shrugged off a revenue miss and celebrated a rebound in gross margins.",
      "link": "https://www.marketwatch.com/story/super-micros-stock-surges-as-wall-street-cheers-a-margin-recovery-80f17361?mod=mw_rss_topstories",
      "source": "MarketWatch Top Stories",
      "category": "financial",
      "sentiment": "positive",
      "impact_score": 100,
      "timestamp": "2026-05-06T06:16:39.835215+00:00",
      "published": "Wed, 06 May 2026 00:31:00 GMT"
    },
    {
      "title": "Upstart\u2019s stock is getting punished after earnings. Here\u2019s the big gripe.",
      "summary": "The AI lending company came up short on a key profit metric, but its CEO says that analysts may have mismodeled seasonal trends.",
      "link": "https://www.marketwatch.com/story/upstarts-stock-is-getting-punished-after-earnings-heres-the-big-gripe-6d27ca70?mod=mw_rss_topstories",
      "source": "MarketWatch Top Stories",
      "category": "financial",
      "sentiment": "positive",
      "impact_score": 100,
      "timestamp": "2026-05-06T06:16:39.835246+00:00",
      "published": "Wed, 06 May 2026 00:30:00 GMT"
    },
    {
      "title": "The last time semiconductor stocks rose this far this quickly, the dot-com bubble burst",
      "summary": "The rolling 25-day performance for one index of semiconductor stocks has reached its highest level since March 9, 2000 \u2014the day before the dot-com bubble peaked.",
      "link": "https://www.marketwatch.com/story/the-last-time-semiconductor-stocks-rose-this-far-this-quickly-the-dot-com-bubble-burst-d7b6666b?mod=mw_rss_topstories",
      "source": "MarketWatch Top Stories",
      "category": "financial",
      "sentiment": "neutral",
      "impact_score": 100,
      "timestamp": "2026-05-06T06:16:39.835286+00:00",
      "published": "Tue, 05 May 2026 23:17:00 GMT"
    },
    {
      "title": "North Korea terror victims escalate fight to seize $71 million from Aave hack",
      "summary": "",
      "link": "https://www.coindesk.com/policy/2026/05/06/north-korea-terror-victims-escalate-fight-to-seize-usd71-million-from-aave-hack",
      "source": "CoinDesk",
      "category": "crypto",
      "sentiment": "neutral",
      "impact_score": 100,
      "timestamp": "2026-05-06T06:16:34.646029+00:00",
      "published": "Wed, 06 May 2026 05:09:22 +0000"
    },
    {
      "title": "XRP above $1.42 as traders watch 2025 breakout pattern that led to 66% rally",
      "summary": "",
      "link": "https://www.coindesk.com/markets/2026/05/06/xrp-above-usd1-42-as-traders-watch-2025-breakout-pattern-that-led-to-66-rally",
      "source": "CoinDesk",
      "category": "crypto",
      "sentiment": "positive",
      "impact_score": 100,
      "timestamp": "2026-05-06T06:16:34.646086+00:00",
      "published": "Wed, 06 May 2026 04:25:26 +0000"
    },
    {
      "title": "Bitcoin tops $81,000 as Strategy mulls selling its BTC to fund dividend obligations",
      "summary": "",
      "link": "https://www.coindesk.com/markets/2026/05/06/bitcoin-tops-usd81-000-as-strategy-mulls-selling-its-btc-to-fund-dividend-obligations",
      "source": "CoinDesk",
      "category": "crypto",
      "sentiment": "neutral",
      "impact_score": 100,
      "timestamp": "2026-05-06T06:16:34.646107+00:00",
      "published": "Wed, 06 May 2026 04:11:27 +0000"
    },
    {
      "title": "Michael Saylor's Strategy signals potential bitcoin sale to fund dividends obligations",
      "summary": "",
      "link": "https://www.coindesk.com/business/2026/05/05/michael-saylor-s-strategy-signals-potential-bitcoin-sale-to-fund-dividends-obligations",
      "source": "CoinDesk",
      "category": "crypto",
      "sentiment": "neutral",
      "impact_score": 100,
      "timestamp": "2026-05-06T06:16:34.646124+00:00",
      "published": "Tue, 05 May 2026 23:43:44 +0000"
    },
    {
      "title": "Trust in crypto remains biggest barrier to adoption, say Consensus Miami 2026 panelists",
      "summary": "",
      "link": "https://www.coindesk.com/policy/2026/05/05/trust-in-crypto-remains-biggest-barrier-to-adoption-say-consensus-miami-2026-panelists",
      "source": "CoinDesk",
      "category": "crypto",
      "sentiment": "positive",
      "impact_score": 100,
      "timestamp": "2026-05-06T06:16:34.646141+00:00",
      "published": "Tue, 05 May 2026 22:39:33 +0000"
    }
  ],
  "categories": {
    "crypto": [
      {
        "title": "North Korea terror victims escalate fight to seize $71 million from Aave hack",
        "summary": "",
        "link": "https://www.coindesk.com/policy/2026/05/06/north-korea-terror-victims-escalate-fight-to-seize-usd71-million-from-aave-hack",
        "source": "CoinDesk",
        "category": "crypto",
        "sentiment": "neutral",
        "impact_score": 100,
        "timestamp": "2026-05-06T06:16:34.646029+00:00",
        "published": "Wed, 06 May 2026 05:09:22 +0000"
      },
      {
        "title": "XRP above $1.42 as traders watch 2025 breakout pattern that led to 66% rally",
        "summary": "",
        "link": "https://www.coindesk.com/markets/2026/05/06/xrp-above-usd1-42-as-traders-watch-2025-breakout-pattern-that-led-to-66-rally",
        "source": "CoinDesk",
        "category": "crypto",
        "sentiment": "positive",
        "impact_score": 100,
        "timestamp": "2026-05-06T06:16:34.646086+00:00",
        "published": "Wed, 06 May 2026 04:25:26 +0000"
      },
      {
        "title": "Bitcoin tops $81,000 as Strategy mulls selling its BTC to fund dividend obligations",
        "summary": "",
        "link": "https://www.coindesk.com/markets/2026/05/06/bitcoin-tops-usd81-000-as-strategy-mulls-selling-its-btc-to-fund-dividend-obligations",
        "source": "CoinDesk",
        "category": "crypto",
        "sentiment": "neutral",
        "impact_score": 100,
        "timestamp": "2026-05-06T06:16:34.646107+00:00",
        "published": "Wed, 06 May 2026 04:11:27 +0000"
      },
      {
        "title": "Michael Saylor's Strategy signals potential bitcoin sale to fund dividends obligations",
        "summary": "",
        "link": "https://www.coindesk.com/business/2026/05/05/michael-saylor-s-strategy-signals-potential-bitcoin-sale-to-fund-dividends-obligations",
        "source": "CoinDesk",
        "category": "crypto",
        "sentiment": "neutral",
        "impact_score": 100,
        "timestamp": "2026-05-06T06:16:34.646124+00:00",
        "published": "Tue, 05 May 2026 23:43:44 +0000"
      },
      {
        "title": "Trust in crypto remains biggest barrier to adoption, say Consensus Miami 2026 panelists",
        "summary": "",
        "link": "https://www.coindesk.com/policy/2026/05/05/trust-in-crypto-remains-biggest-barrier-to-adoption-say-consensus-miami-2026-panelists",
        "source": "CoinDesk",
        "category": "crypto",
        "sentiment": "positive",
        "impact_score": 100,
        "timestamp": "2026-05-06T06:16:34.646141+00:00",
        "published": "Tue, 05 May 2026 22:39:33 +0000"
      }
    ],
    "financial": [
      {
        "title": "Michael Burry sells entire stake in surging meme-stock giant",
        "summary": "",
        "link": "https://finance.yahoo.com/markets/stocks/articles/michael-burry-sells-entire-stake-202300350.html",
        "source": "Yahoo Finance",
        "category": "financial",
        "sentiment": "neutral",
        "impact_score": 100,
        "timestamp": "2026-05-06T06:16:36.425242+00:00",
        "published": "2026-05-05T20:23:00Z"
      },
      {
        "title": "Alarm bells raised over fintech firm\u2019s bank purchase",
        "summary": "",
        "link": "https://finance.yahoo.com/economy/policy/articles/alarm-bells-raised-over-fintech-030700036.html",
        "source": "Yahoo Finance",
        "category": "financial",
        "sentiment": "negative",
        "impact_score": 100,
        "timestamp": "2026-05-06T06:16:36.425291+00:00",
        "published": "2026-05-05T03:07:00Z"
      },
      {
        "title": "Jim Cramer on Cloudflare: \u201cThey\u2019re a Terrific Cyber Defender\u201d",
        "summary": "",
        "link": "https://finance.yahoo.com/markets/stocks/articles/jim-cramer-cloudflare-terrific-cyber-184731835.html",
        "source": "Yahoo Finance",
        "category": "financial",
        "sentiment": "neutral",
        "impact_score": 100,
        "timestamp": "2026-05-06T06:16:36.425318+00:00",
        "published": "2026-05-04T18:47:31Z"
      },
      {
        "title": "Jim Cramer Explains Why Berkshire Hathaway \u201cUnderperformed of Late\u201d",
        "summary": "",
        "link": "https://finance.yahoo.com/markets/stocks/articles/jim-cramer-explains-why-berkshire-184733352.html",
        "source": "Yahoo Finance",
        "category": "financial",
        "sentiment": "neutral",
        "impact_score": 100,
        "timestamp": "2026-05-06T06:16:36.425341+00:00",
        "published": "2026-05-04T18:47:33Z"
      },
      {
        "title": "Jim Cramer on Merck & Co.: \u201cThe Stock\u2019s Starting to Come Back\u201d",
        "summary": "",
        "link": "https://finance.yahoo.com/markets/stocks/articles/jim-cramer-merck-co-stock-184817086.html",
        "source": "Yahoo Finance",
        "category": "financial",
        "sentiment": "neutral",
        "impact_score": 100,
        "timestamp": "2026-05-06T06:16:36.425359+00:00",
        "published": "2026-05-04T18:48:17Z"
      }
    ],
    "general": [
      {
        "title": "What is Trump's 'Project Freedom' in the Strait of Hormuz?",
        "summary": "The US president said the operation has been paused after starting on Monday.",
        "link": "https://www.bbc.com/news/articles/c4g437depzpo?at_medium=RSS&at_campaign=rss",
        "source": "BBC News",
        "category": "general",
        "sentiment": "neutral",
        "impact_score": 100,
        "timestamp": "2026-05-06T06:16:39.160425+00:00",
        "published": "Wed, 06 May 2026 02:23:36 GMT"
      },
      {
        "title": "Cruise ship with hantavirus outbreak to sail to Canary Islands",
        "summary": "Spain's health ministry said the MV Hondius is expected to arrive within three to four days.",
        "link": "https://www.bbc.com/news/articles/ce8pypvjx1ko?at_medium=RSS&at_campaign=rss",
        "source": "BBC News",
        "category": "general",
        "sentiment": "neutral",
        "impact_score": 100,
        "timestamp": "2026-05-06T06:16:39.160521+00:00",
        "published": "Wed, 06 May 2026 00:01:28 GMT"
      },
      {
        "title": "'Nothing will bring back my son': How 10 minutes of bombing by Israel shattered lives in Lebanon",
        "summary": "The bombs started falling at 14:15 in the afternoon - bringing chaos and destruction across the country.",
        "link": "https://www.bbc.com/news/articles/c202652vvnjo?at_medium=RSS&at_campaign=rss",
        "source": "BBC News",
        "category": "general",
        "sentiment": "negative",
        "impact_score": 100,
        "timestamp": "2026-05-06T06:16:39.160571+00:00",
        "published": "Tue, 05 May 2026 21:22:31 GMT"
      },
      {
        "title": "Catherine to return to overseas visits with Italy trip",
        "summary": "The Princess of Wales will go to Italy next week on her first official overseas engagement for more than three years.",
        "link": "https://www.bbc.com/news/articles/c707k90lplno?at_medium=RSS&at_campaign=rss",
        "source": "BBC News",
        "category": "general",
        "sentiment": "neutral",
        "impact_score": 100,
        "timestamp": "2026-05-06T06:16:39.160600+00:00",
        "published": "Wed, 06 May 2026 00:04:38 GMT"
      },
      {
        "title": "Campaigning sprint finish ahead of elections around Britain tomorrow",
        "summary": "A mesmerising mix of results are expected after candidates make their final pitches, our political editor writes.",
        "link": "https://www.bbc.com/news/articles/c759z9w7z3yo?at_medium=RSS&at_campaign=rss",
        "source": "BBC News",
        "category": "general",
        "sentiment": "neutral",
        "impact_score": 100,
        "timestamp": "2026-05-06T06:16:39.160627+00:00",
        "published": "Wed, 06 May 2026 00:15:28 GMT"
      }
    ]
  },
  "analysis": {
    "market_context": "Breaking news may create short-term market movements",
    "watch_items": [
      "Regulatory: Iggy Azalea faces class lawsuit over MOTHER memecoin...",
      "Crypto: North Korea terror victims escalate fight to seize $71 milli..."
    ],
    "source_health": [
      {
        "source": "CoinDesk",
        "category": "crypto",
        "fetched": 5,
        "ok": true,
        "error": null
      },
      {
        "source": "Cointelegraph",
        "category": "crypto",
        "fetched": 5,
        "ok": true,
        "error": null
      },
      {
        "source": "Reuters Business",
        "category": "financial",
        "fetched": 0,
        "ok": false,
        "error": null
      },
      {
        "source": "Yahoo Finance",
        "category": "financial",
        "fetched": 5,
        "ok": true,
        "error": null
      },
      {
        "source": "AP News",
        "category": "general",
        "fetched": 0,
        "ok": false,
        "error": null
      },
      {
        "source": "BBC News",
        "category": "general",
        "fetched": 5,
        "ok": true,
        "error": null
      },
      {
        "source": "MarketWatch Top Stories",
        "category": "financial",
        "fetched": 5,
        "ok": true,
        "error": null
      },
      {
        "source": "Investing.com",
        "category": "financial",
        "fetched": 5,
        "ok": true,
        "error": null
      }
    ],
    "source_diversity": 6,
    "source_summary": [
      "CoinDesk: ok (5 items)",
      "Cointelegraph: ok (5 items)",
      "Reuters Business: weak (0 items)",
      "Yahoo Finance: ok (5 items)",
      "AP News: weak (0 items)",
      "BBC News: ok (5 items)",
      "MarketWatch Top Stories: ok (5 items)",
      "Investing.com: ok (5 items)"
    ]
  }
}