{
  "schema_version": "1.0.0",
  "generated_at": "2026-04-24T20:02:36.013937+00:00",
  "generated_at_utc": "2026-04-24T20:02:36.013946+00:00",
  "summary": {
    "total_articles": 25,
    "overall_sentiment": "neutral",
    "sentiment_breakdown": {
      "positive": 4.0,
      "neutral": 76.0,
      "negative": 20.0
    },
    "breaking_news_count": 3
  },
  "trends": {
    "overall_sentiment": "neutral",
    "sentiment_counts": {
      "positive": 1,
      "neutral": 19,
      "negative": 5
    },
    "sentiment_percentages": {
      "positive": 4.0,
      "neutral": 76.0,
      "negative": 20.0
    },
    "category_counts": {
      "financial": 15,
      "crypto": 5,
      "general": 5
    },
    "breaking_news": [
      {
        "title": "JPMorgan issues blunt warning as investors move to safety",
        "source": "Yahoo Finance",
        "sentiment": "negative",
        "impact": 100
      },
      {
        "title": "Exclusive-SpaceX IPO filing shows Elon Musk can retain board control",
        "source": "Yahoo Finance",
        "sentiment": "neutral",
        "impact": 100
      },
      {
        "title": "Netflix boosts share buyback plan by $25 billion after failed Warner Bros bid",
        "source": "Yahoo Finance",
        "sentiment": "neutral",
        "impact": 100
      }
    ]
  },
  "top_articles": [
    {
      "title": "JPMorgan issues blunt warning as investors move to safety",
      "summary": "",
      "link": "https://finance.yahoo.com/markets/crypto/articles/jpmorgan-issues-blunt-warning-investors-193000280.html",
      "source": "Yahoo Finance",
      "category": "financial",
      "sentiment": "negative",
      "impact_score": 100,
      "timestamp": "2026-04-24T20:02:29.212490+00:00",
      "published": "2026-04-23T19:30:00Z"
    },
    {
      "title": "Exclusive-SpaceX IPO filing shows Elon Musk can retain board control",
      "summary": "",
      "link": "https://finance.yahoo.com/markets/stocks/articles/exclusive-spacex-ipo-filing-shows-100631775.html",
      "source": "Yahoo Finance",
      "category": "financial",
      "sentiment": "neutral",
      "impact_score": 100,
      "timestamp": "2026-04-24T20:02:29.212513+00:00",
      "published": "2026-04-23T10:18:59Z"
    },
    {
      "title": "Netflix boosts share buyback plan by $25 billion after failed Warner Bros bid",
      "summary": "",
      "link": "https://finance.yahoo.com/markets/stocks/articles/netflix-announces-25-billion-share-101845782.html",
      "source": "Yahoo Finance",
      "category": "financial",
      "sentiment": "neutral",
      "impact_score": 100,
      "timestamp": "2026-04-24T20:02:29.212527+00:00",
      "published": "2026-04-23T10:18:45Z"
    },
    {
      "title": "Exclusive-Advent-owned firm investigated in Brazil for alleged links to organized crime",
      "summary": "",
      "link": "https://finance.yahoo.com/economy/articles/exclusive-advent-owned-firm-investigated-101302265.html",
      "source": "Yahoo Finance",
      "category": "financial",
      "sentiment": "neutral",
      "impact_score": 100,
      "timestamp": "2026-04-24T20:02:29.212538+00:00",
      "published": "2026-04-23T10:20:39Z"
    },
    {
      "title": "Exclusive-SpaceX conquered the stars, now eyes bigger opportunity in AI",
      "summary": "",
      "link": "https://finance.yahoo.com/sectors/technology/articles/exclusive-spacex-conquered-stars-now-100320916.html",
      "source": "Yahoo Finance",
      "category": "financial",
      "sentiment": "neutral",
      "impact_score": 100,
      "timestamp": "2026-04-24T20:02:29.212548+00:00",
      "published": "2026-04-23T10:19:34Z"
    },
    {
      "title": "Charter\u2019s stock is getting hammered. Here\u2019s what\u2019s fueling its worst day on record.",
      "summary": "Charter lost more internet subscribers than expected in the latest quarter, signaling that the company isn\u2019t out of the woods when it comes to broadband woes.",
      "link": "https://www.marketwatch.com/story/charters-stock-is-getting-hammered-heres-whats-fueling-its-worst-day-on-record-11f991a0?mod=mw_rss_topstories",
      "source": "MarketWatch Top Stories",
      "category": "financial",
      "sentiment": "negative",
      "impact_score": 100,
      "timestamp": "2026-04-24T20:02:34.533853+00:00",
      "published": "Fri, 24 Apr 2026 19:34:00 GMT"
    },
    {
      "title": "Why crude prices won\u2019t fall back to levels seen before the Iran war anytime soon",
      "summary": "SLB and Halliburton both said this week they expect crude prices to remain higher for longer. That will have immediate implications for a host of products \u2014 none as scrutinized as gasoline.",
      "link": "https://www.marketwatch.com/story/why-crude-prices-wont-fall-back-to-levels-seen-before-the-iran-war-anytime-soon-9bdceed1?mod=mw_rss_topstories",
      "source": "MarketWatch Top Stories",
      "category": "financial",
      "sentiment": "negative",
      "impact_score": 100,
      "timestamp": "2026-04-24T20:02:34.533896+00:00",
      "published": "Fri, 24 Apr 2026 19:07:00 GMT"
    },
    {
      "title": "Nvidia\u2019s stock heads for first record close in 6 months \u2014 thanks to Intel",
      "summary": "Nvidia is finally on track to finish back in $5 trillion territory, capping off an \u201cincredible week\u201d for chip makers.",
      "link": "https://www.marketwatch.com/story/nvidias-stock-heads-for-first-record-close-in-6-months-thanks-to-intel-21af7d28?mod=mw_rss_topstories",
      "source": "MarketWatch Top Stories",
      "category": "financial",
      "sentiment": "neutral",
      "impact_score": 100,
      "timestamp": "2026-04-24T20:02:34.533921+00:00",
      "published": "Fri, 24 Apr 2026 19:06:00 GMT"
    },
    {
      "title": "After suspicious Polymarket bets, French weather forecast office files police complaint",
      "summary": "Temperature readings at Charles de Gaulle International Airport rose by a few degrees in a matter of minutes.",
      "link": "https://www.marketwatch.com/story/french-weather-forecasting-office-files-police-complaint-following-suspicious-surge-in-polymarket-bets-fb72729d?mod=mw_rss_topstories",
      "source": "MarketWatch Top Stories",
      "category": "financial",
      "sentiment": "neutral",
      "impact_score": 100,
      "timestamp": "2026-04-24T20:02:34.533942+00:00",
      "published": "Fri, 24 Apr 2026 18:32:00 GMT"
    },
    {
      "title": "Medicare Advantage buyers beware: The rules for selling plans are changing \u2014 and could harm seniors",
      "summary": "The marketing rules behind Medicare Advantage are about to get looser, benefitting brokers and agents that sell the private-insurance alternative to traditional Medicare",
      "link": "https://www.marketwatch.com/story/medicare-advantage-buyers-beware-the-rules-for-selling-plans-are-changing-and-could-harm-seniors-77f5daae?mod=mw_rss_topstories",
      "source": "MarketWatch Top Stories",
      "category": "financial",
      "sentiment": "neutral",
      "impact_score": 100,
      "timestamp": "2026-04-24T20:02:34.533968+00:00",
      "published": "Fri, 24 Apr 2026 18:11:00 GMT"
    },
    {
      "title": "Tether's $344 million USDT freeze linked to U.S. 'Economic Fury' against Iran regime",
      "summary": "",
      "link": "https://www.coindesk.com/policy/2026/04/24/tether-s-usd344-million-usdt-freeze-linked-to-u-s-economic-fury-against-iran-regime",
      "source": "CoinDesk",
      "category": "crypto",
      "sentiment": "positive",
      "impact_score": 100,
      "timestamp": "2026-04-24T20:02:26.574720+00:00",
      "published": "Fri, 24 Apr 2026 19:50:07 +0000"
    },
    {
      "title": "Trump's DOJ drops probe that stood in way of president's pick to run Federal Reserve",
      "summary": "",
      "link": "https://www.coindesk.com/news-analysis/2026/04/24/trump-s-doj-drops-probe-that-stood-in-way-of-president-s-pick-to-run-federal-reserve",
      "source": "CoinDesk",
      "category": "crypto",
      "sentiment": "negative",
      "impact_score": 100,
      "timestamp": "2026-04-24T20:02:26.574761+00:00",
      "published": "Fri, 24 Apr 2026 16:38:39 +0000"
    },
    {
      "title": "Jane Street asks court to reject Terraform claims tied to UST-LUNA crash",
      "summary": "",
      "link": "https://www.coindesk.com/policy/2026/04/24/jane-street-asks-court-to-reject-terraform-claims-tied-to-ust-luna-crash",
      "source": "CoinDesk",
      "category": "crypto",
      "sentiment": "negative",
      "impact_score": 100,
      "timestamp": "2026-04-24T20:02:26.574777+00:00",
      "published": "Fri, 24 Apr 2026 15:53:44 +0000"
    },
    {
      "title": "Bitmine to buy 10,000 ether for $23.9 million from the Ethereum Foundation",
      "summary": "",
      "link": "https://www.coindesk.com/business/2026/04/24/bitmine-to-buy-10-000-ether-for-usd23-8-million-from-the-ethereum-foundation",
      "source": "CoinDesk",
      "category": "crypto",
      "sentiment": "neutral",
      "impact_score": 100,
      "timestamp": "2026-04-24T20:02:26.574789+00:00",
      "published": "Fri, 24 Apr 2026 15:47:48 +0000"
    },
    {
      "title": "Researcher wins 1 bitcoin bounty for 'largest quantum attack' on underlying tech",
      "summary": "",
      "link": "https://www.coindesk.com/tech/2026/04/24/researcher-wins-1-bitcoin-bounty-for-largest-quantum-attack-on-underlying-tech",
      "source": "CoinDesk",
      "category": "crypto",
      "sentiment": "neutral",
      "impact_score": 100,
      "timestamp": "2026-04-24T20:02:26.574799+00:00",
      "published": "Fri, 24 Apr 2026 15:14:31 +0000"
    }
  ],
  "categories": {
    "crypto": [
      {
        "title": "Tether's $344 million USDT freeze linked to U.S. 'Economic Fury' against Iran regime",
        "summary": "",
        "link": "https://www.coindesk.com/policy/2026/04/24/tether-s-usd344-million-usdt-freeze-linked-to-u-s-economic-fury-against-iran-regime",
        "source": "CoinDesk",
        "category": "crypto",
        "sentiment": "positive",
        "impact_score": 100,
        "timestamp": "2026-04-24T20:02:26.574720+00:00",
        "published": "Fri, 24 Apr 2026 19:50:07 +0000"
      },
      {
        "title": "Trump's DOJ drops probe that stood in way of president's pick to run Federal Reserve",
        "summary": "",
        "link": "https://www.coindesk.com/news-analysis/2026/04/24/trump-s-doj-drops-probe-that-stood-in-way-of-president-s-pick-to-run-federal-reserve",
        "source": "CoinDesk",
        "category": "crypto",
        "sentiment": "negative",
        "impact_score": 100,
        "timestamp": "2026-04-24T20:02:26.574761+00:00",
        "published": "Fri, 24 Apr 2026 16:38:39 +0000"
      },
      {
        "title": "Jane Street asks court to reject Terraform claims tied to UST-LUNA crash",
        "summary": "",
        "link": "https://www.coindesk.com/policy/2026/04/24/jane-street-asks-court-to-reject-terraform-claims-tied-to-ust-luna-crash",
        "source": "CoinDesk",
        "category": "crypto",
        "sentiment": "negative",
        "impact_score": 100,
        "timestamp": "2026-04-24T20:02:26.574777+00:00",
        "published": "Fri, 24 Apr 2026 15:53:44 +0000"
      },
      {
        "title": "Bitmine to buy 10,000 ether for $23.9 million from the Ethereum Foundation",
        "summary": "",
        "link": "https://www.coindesk.com/business/2026/04/24/bitmine-to-buy-10-000-ether-for-usd23-8-million-from-the-ethereum-foundation",
        "source": "CoinDesk",
        "category": "crypto",
        "sentiment": "neutral",
        "impact_score": 100,
        "timestamp": "2026-04-24T20:02:26.574789+00:00",
        "published": "Fri, 24 Apr 2026 15:47:48 +0000"
      },
      {
        "title": "Researcher wins 1 bitcoin bounty for 'largest quantum attack' on underlying tech",
        "summary": "",
        "link": "https://www.coindesk.com/tech/2026/04/24/researcher-wins-1-bitcoin-bounty-for-largest-quantum-attack-on-underlying-tech",
        "source": "CoinDesk",
        "category": "crypto",
        "sentiment": "neutral",
        "impact_score": 100,
        "timestamp": "2026-04-24T20:02:26.574799+00:00",
        "published": "Fri, 24 Apr 2026 15:14:31 +0000"
      }
    ],
    "financial": [
      {
        "title": "JPMorgan issues blunt warning as investors move to safety",
        "summary": "",
        "link": "https://finance.yahoo.com/markets/crypto/articles/jpmorgan-issues-blunt-warning-investors-193000280.html",
        "source": "Yahoo Finance",
        "category": "financial",
        "sentiment": "negative",
        "impact_score": 100,
        "timestamp": "2026-04-24T20:02:29.212490+00:00",
        "published": "2026-04-23T19:30:00Z"
      },
      {
        "title": "Exclusive-SpaceX IPO filing shows Elon Musk can retain board control",
        "summary": "",
        "link": "https://finance.yahoo.com/markets/stocks/articles/exclusive-spacex-ipo-filing-shows-100631775.html",
        "source": "Yahoo Finance",
        "category": "financial",
        "sentiment": "neutral",
        "impact_score": 100,
        "timestamp": "2026-04-24T20:02:29.212513+00:00",
        "published": "2026-04-23T10:18:59Z"
      },
      {
        "title": "Netflix boosts share buyback plan by $25 billion after failed Warner Bros bid",
        "summary": "",
        "link": "https://finance.yahoo.com/markets/stocks/articles/netflix-announces-25-billion-share-101845782.html",
        "source": "Yahoo Finance",
        "category": "financial",
        "sentiment": "neutral",
        "impact_score": 100,
        "timestamp": "2026-04-24T20:02:29.212527+00:00",
        "published": "2026-04-23T10:18:45Z"
      },
      {
        "title": "Exclusive-Advent-owned firm investigated in Brazil for alleged links to organized crime",
        "summary": "",
        "link": "https://finance.yahoo.com/economy/articles/exclusive-advent-owned-firm-investigated-101302265.html",
        "source": "Yahoo Finance",
        "category": "financial",
        "sentiment": "neutral",
        "impact_score": 100,
        "timestamp": "2026-04-24T20:02:29.212538+00:00",
        "published": "2026-04-23T10:20:39Z"
      },
      {
        "title": "Exclusive-SpaceX conquered the stars, now eyes bigger opportunity in AI",
        "summary": "",
        "link": "https://finance.yahoo.com/sectors/technology/articles/exclusive-spacex-conquered-stars-now-100320916.html",
        "source": "Yahoo Finance",
        "category": "financial",
        "sentiment": "neutral",
        "impact_score": 100,
        "timestamp": "2026-04-24T20:02:29.212548+00:00",
        "published": "2026-04-23T10:19:34Z"
      }
    ],
    "general": [
      {
        "title": "Chris Mason: A grim week for Starmer \u2013 but things could be about to get worse",
        "summary": "The Mandelson vetting row has reignited questions over the PM's future just two weeks before crucial elections in Scotland, Wales and England.",
        "link": "https://www.bbc.com/news/articles/cvg423lnlp5o?at_medium=RSS&at_campaign=rss",
        "source": "BBC News",
        "category": "general",
        "sentiment": "neutral",
        "impact_score": 100,
        "timestamp": "2026-04-24T20:02:32.745395+00:00",
        "published": "Fri, 24 Apr 2026 17:16:12 GMT"
      },
      {
        "title": "No 10 says Falklands sovereignty rests with UK after report of US 'review'",
        "summary": "An internal Pentagon document reportedly raised the prospect of a change in position in retaliation for the UK not joining the Iran war.",
        "link": "https://www.bbc.com/news/articles/cde51y0zgjyo?at_medium=RSS&at_campaign=rss",
        "source": "BBC News",
        "category": "general",
        "sentiment": "neutral",
        "impact_score": 100,
        "timestamp": "2026-04-24T20:02:32.745445+00:00",
        "published": "Fri, 24 Apr 2026 17:37:28 GMT"
      },
      {
        "title": "US looks to Falklands as opportunity for diplomatic pressure on UK",
        "summary": "This story will make greater waves in the UK than in the US, which for Donald Trump is an opportunity for leverage, Joe Inwood writes.",
        "link": "https://www.bbc.com/news/articles/cly7w3zjl38o?at_medium=RSS&at_campaign=rss",
        "source": "BBC News",
        "category": "general",
        "sentiment": "neutral",
        "impact_score": 100,
        "timestamp": "2026-04-24T20:02:32.745475+00:00",
        "published": "Fri, 24 Apr 2026 13:26:07 GMT"
      },
      {
        "title": "'My living nightmare': Rob Reiner's son on how he found out parents were dead",
        "summary": "The actor says the grief of his parents' brutal deaths and the arrest of his own brother left him in a \"trance\".",
        "link": "https://www.bbc.com/news/articles/c74v2enw8l7o?at_medium=RSS&at_campaign=rss",
        "source": "BBC News",
        "category": "general",
        "sentiment": "neutral",
        "impact_score": 100,
        "timestamp": "2026-04-24T20:02:32.745502+00:00",
        "published": "Fri, 24 Apr 2026 18:02:54 GMT"
      },
      {
        "title": "UK cyber chiefs say it's time to ditch passwords for passkeys - what are they?",
        "summary": "Passwords have long been the default way we secure accounts online but the NCSC has said passkeys are a better option.",
        "link": "https://www.bbc.com/news/articles/cq8wnzly5j5o?at_medium=RSS&at_campaign=rss",
        "source": "BBC News",
        "category": "general",
        "sentiment": "neutral",
        "impact_score": 100,
        "timestamp": "2026-04-24T20:02:32.745527+00:00",
        "published": "Fri, 24 Apr 2026 14:40:23 GMT"
      }
    ]
  },
  "analysis": {
    "market_context": "Breaking news may create short-term market movements",
    "watch_items": [
      "Regulatory: Trump's DOJ drops probe that stood in way of president's pic...",
      "Crypto: Tether's $344 million USDT freeze linked to U.S. 'Economic F..."
    ],
    "source_health": [
      {
        "source": "CoinDesk",
        "category": "crypto",
        "fetched": 5,
        "ok": true,
        "error": null
      },
      {
        "source": "Cointelegraph",
        "category": "crypto",
        "fetched": 0,
        "ok": false,
        "error": null
      },
      {
        "source": "Reuters Business",
        "category": "financial",
        "fetched": 0,
        "ok": false,
        "error": null
      },
      {
        "source": "Yahoo Finance",
        "category": "financial",
        "fetched": 5,
        "ok": true,
        "error": null
      },
      {
        "source": "AP News",
        "category": "general",
        "fetched": 0,
        "ok": false,
        "error": null
      },
      {
        "source": "BBC News",
        "category": "general",
        "fetched": 5,
        "ok": true,
        "error": null
      },
      {
        "source": "MarketWatch Top Stories",
        "category": "financial",
        "fetched": 5,
        "ok": true,
        "error": null
      },
      {
        "source": "Investing.com",
        "category": "financial",
        "fetched": 5,
        "ok": true,
        "error": null
      }
    ],
    "source_diversity": 5,
    "source_summary": [
      "CoinDesk: ok (5 items)",
      "Cointelegraph: weak (0 items)",
      "Reuters Business: weak (0 items)",
      "Yahoo Finance: ok (5 items)",
      "AP News: weak (0 items)",
      "BBC News: ok (5 items)",
      "MarketWatch Top Stories: ok (5 items)",
      "Investing.com: ok (5 items)"
    ]
  }
}