{
  "schema_version": "1.0.0",
  "ledger_type": "simulated_crypto_trade_ledger",
  "generated_at_utc": "2026-05-12T08:05:22Z",
  "simulated": true,
  "real_order": false,
  "execution_mode": "paper_only_no_exchange_orders",
  "private_credentials_used": false,
  "order_routing_enabled": false,
  "risk_policy": {
    "risk_per_trade_fraction": 0.01,
    "risk_per_trade_cap_pct": 1.0,
    "max_concurrent_positions": 5,
    "max_concurrent_positions_cap": 5,
    "watchlist_handling": "track_only_no_fill",
    "real_orders_allowed": false
  },
  "sources": {
    "dashboard_data": "dashboard/site/dashboard-data.json",
    "dashboard_generator": "generate_dashboard_data.py",
    "data_provenance": {
      "crypto_market_data": {
        "source_name": "Binance public realtime market data",
        "public_endpoint_only": true,
        "private_credentials_used": false,
        "real_order": false,
        "generated_at_utc": "2026-05-12T08:05:22Z",
        "preferred_market_type": "spot",
        "kline_interval": "1h",
        "kline_limit": 120,
        "live_spot_symbols": [
          "BTC",
          "ETH",
          "SOL",
          "ZEC",
          "SENT",
          "ASTER"
        ],
        "binance_futures_fallback_symbols": [
          "HYPE"
        ],
        "existing_source_fallback_symbols": [],
        "missing_symbols": [],
        "symbols": {
          "BTC": {
            "source_name": "Binance Spot Public",
            "source": "binance-spot-public",
            "primary": true,
            "public_endpoint_only": true,
            "private_credentials_used": false,
            "real_order": false,
            "symbol": "BTC",
            "symbol_pair": "BTCUSDT",
            "market_type": "spot",
            "endpoint": "/api/v3/ticker/24hr + /api/v3/klines",
            "method": "GET",
            "interval": "1h",
            "limit": 120,
            "data_timestamp_utc": "2026-05-12T08:05:23Z",
            "fetched_at_utc": "2026-05-12T08:05:23Z",
            "fallback_reason": null
          },
          "ETH": {
            "source_name": "Binance Spot Public",
            "source": "binance-spot-public",
            "primary": true,
            "public_endpoint_only": true,
            "private_credentials_used": false,
            "real_order": false,
            "symbol": "ETH",
            "symbol_pair": "ETHUSDT",
            "market_type": "spot",
            "endpoint": "/api/v3/ticker/24hr + /api/v3/klines",
            "method": "GET",
            "interval": "1h",
            "limit": 120,
            "data_timestamp_utc": "2026-05-12T08:05:23Z",
            "fetched_at_utc": "2026-05-12T08:05:24Z",
            "fallback_reason": null
          },
          "SOL": {
            "source_name": "Binance Spot Public",
            "source": "binance-spot-public",
            "primary": true,
            "public_endpoint_only": true,
            "private_credentials_used": false,
            "real_order": false,
            "symbol": "SOL",
            "symbol_pair": "SOLUSDT",
            "market_type": "spot",
            "endpoint": "/api/v3/ticker/24hr + /api/v3/klines",
            "method": "GET",
            "interval": "1h",
            "limit": 120,
            "data_timestamp_utc": "2026-05-12T08:05:23Z",
            "fetched_at_utc": "2026-05-12T08:05:24Z",
            "fallback_reason": null
          },
          "ZEC": {
            "source_name": "Binance Spot Public",
            "source": "binance-spot-public",
            "primary": true,
            "public_endpoint_only": true,
            "private_credentials_used": false,
            "real_order": false,
            "symbol": "ZEC",
            "symbol_pair": "ZECUSDT",
            "market_type": "spot",
            "endpoint": "/api/v3/ticker/24hr + /api/v3/klines",
            "method": "GET",
            "interval": "1h",
            "limit": 120,
            "data_timestamp_utc": "2026-05-12T08:05:23Z",
            "fetched_at_utc": "2026-05-12T08:05:25Z",
            "fallback_reason": null
          },
          "HYPE": {
            "source_name": "Binance USD-M Futures Public",
            "source": "binance-usdm-futures-public",
            "primary": false,
            "public_endpoint_only": true,
            "private_credentials_used": false,
            "real_order": false,
            "symbol": "HYPE",
            "symbol_pair": "HYPEUSDT",
            "market_type": "usd_m_futures",
            "endpoint": "/fapi/v1/ticker/24hr + /fapi/v1/klines",
            "method": "GET",
            "interval": "1h",
            "limit": 120,
            "data_timestamp_utc": "2026-05-12T08:05:23Z",
            "fetched_at_utc": "2026-05-12T08:05:26Z",
            "fallback_reason": "Binance spot unavailable/unsupported (spot HYPEUSDT: HTTP 400: {\"code\":-1121,\"msg\":\"Invalid symbol.\"}); used Binance public USD-M futures market data."
          },
          "SENT": {
            "source_name": "Binance Spot Public",
            "source": "binance-spot-public",
            "primary": true,
            "public_endpoint_only": true,
            "private_credentials_used": false,
            "real_order": false,
            "symbol": "SENT",
            "symbol_pair": "SENTUSDT",
            "market_type": "spot",
            "endpoint": "/api/v3/ticker/24hr + /api/v3/klines",
            "method": "GET",
            "interval": "1h",
            "limit": 120,
            "data_timestamp_utc": "2026-05-12T08:05:24Z",
            "fetched_at_utc": "2026-05-12T08:05:26Z",
            "fallback_reason": null
          },
          "ASTER": {
            "source_name": "Binance Spot Public",
            "source": "binance-spot-public",
            "primary": true,
            "public_endpoint_only": true,
            "private_credentials_used": false,
            "real_order": false,
            "symbol": "ASTER",
            "symbol_pair": "ASTERUSDT",
            "market_type": "spot",
            "endpoint": "/api/v3/ticker/24hr + /api/v3/klines",
            "method": "GET",
            "interval": "1h",
            "limit": 120,
            "data_timestamp_utc": "2026-05-12T08:05:26Z",
            "fetched_at_utc": "2026-05-12T08:05:27Z",
            "fallback_reason": null
          }
        }
      },
      "notes": [
        "Binance public spot ticker and klines are attempted first for mapped crypto assets.",
        "If Binance spot is unsupported/unavailable, public Binance USD-M futures may be used as a labelled fallback before existing dashboard sources.",
        "No private exchange credentials are used and no real orders are placed."
      ]
    },
    "paper_portfolio": "/root/.openclaw/workspace/market-briefing+/copilot/virtual_portfolio.json"
  },
  "summary": {
    "open_position_count": 0,
    "closed_trade_count": 15,
    "event_count": 19,
    "watch_only_no_fill_count": 3,
    "ready_candidate_no_auto_fill_count": 0,
    "linked_existing_simulated_position_count": 0
  },
  "open_positions": [],
  "closed_trades": [
    {
      "trade_id": "8ab08c7bd53873bc",
      "symbol": "ETH",
      "side": "short",
      "setup_source": "copilot_virtual_portfolio",
      "entry": 2281.89990234375,
      "size": {
        "quantity": 0.43823132,
        "notional_usd": 1000.0,
        "risk_fraction": 0.01,
        "risk_note": "Paper sizing placeholder; no real capital committed."
      },
      "targets": [
        {
          "label": "tp1",
          "price": 2270.72998
        },
        {
          "label": "tp2",
          "price": 2265.840087890625
        }
      ],
      "invalidation": {
        "price": 2283.13501,
        "reason": "Paper stop/invalidation from source decision."
      },
      "status": "closed",
      "timestamps": {
        "opened_at_utc": "2026-04-29T11:31:15.637985+00:00",
        "dashboard_timestamp_utc": "2026-04-28T09:46:39Z",
        "updated_at_utc": null,
        "closed_at_utc": "2026-05-09T07:52:47.338769+00:00"
      },
      "fill_source": "copilot_virtual_portfolio_json",
      "exit_reason": "closed_in_paper_ledger",
      "simulated": true,
      "real_order": false,
      "notes": "Opened automatically by active paper-trading rules on approved_candidate.",
      "exit_price": 2283.13501,
      "realized_pnl": -0.54
    },
    {
      "trade_id": "d41352de686e9e3b",
      "symbol": "BTC",
      "side": "short",
      "setup_source": "watchlist_candidate",
      "entry": 76628.34375,
      "size": {
        "quantity": 0.0058725,
        "notional_usd": 450.0,
        "risk_fraction": 0.01,
        "risk_note": "Paper sizing placeholder; no real capital committed."
      },
      "targets": [
        {
          "label": "tp1",
          "price": 76504.703125
        },
        {
          "label": "tp2",
          "price": 76472.7578125
        }
      ],
      "invalidation": {
        "price": 76708.585938,
        "reason": "Paper stop/invalidation from source decision."
      },
      "status": "closed",
      "timestamps": {
        "opened_at_utc": "2026-04-30T13:16:38.837102+00:00",
        "dashboard_timestamp_utc": "2026-04-28T09:46:39Z",
        "updated_at_utc": null,
        "closed_at_utc": "2026-05-09T07:52:47.339117+00:00"
      },
      "fill_source": "copilot_virtual_portfolio_json",
      "exit_reason": "closed_in_paper_ledger",
      "simulated": true,
      "real_order": false,
      "notes": "Opened automatically by active paper-trading rules on watchlist_candidate.",
      "exit_price": 76708.585938,
      "realized_pnl": -0.47
    },
    {
      "trade_id": "1b89189f33bdd6c1",
      "symbol": "SOL",
      "side": "short",
      "setup_source": "approved_candidate",
      "entry": 83.25,
      "size": {
        "quantity": 12.32432432,
        "notional_usd": 1026.0,
        "risk_fraction": 0.01,
        "risk_note": "Paper sizing placeholder; no real capital committed."
      },
      "targets": [
        {
          "label": "tp1",
          "price": 82.14
        },
        {
          "label": "tp2",
          "price": 81.39
        }
      ],
      "invalidation": {
        "price": 84.75,
        "reason": "Paper stop/invalidation from source decision."
      },
      "status": "closed",
      "timestamps": {
        "opened_at_utc": "2026-04-30T13:27:47.373697+00:00",
        "dashboard_timestamp_utc": "2026-04-30T13:03:40Z",
        "updated_at_utc": null,
        "closed_at_utc": "2026-05-09T07:52:47.339234+00:00"
      },
      "fill_source": "copilot_virtual_portfolio_json",
      "exit_reason": "closed_in_paper_ledger",
      "simulated": true,
      "real_order": false,
      "notes": "Opened automatically by active paper-trading rules on approved_candidate.",
      "exit_price": 84.75,
      "realized_pnl": -18.49
    },
    {
      "trade_id": "268798c91fbd06ae",
      "symbol": "ZEC",
      "side": "long",
      "setup_source": "watchlist_candidate",
      "entry": 330.71,
      "size": {
        "quantity": 1.13755254,
        "notional_usd": 376.2,
        "risk_fraction": 0.01,
        "risk_note": "Paper sizing placeholder; no real capital committed."
      },
      "targets": [
        {
          "label": "tp1",
          "price": 361.5
        },
        {
          "label": "tp2",
          "price": 362.75
        }
      ],
      "invalidation": {
        "price": 329.57,
        "reason": "Paper stop/invalidation from source decision."
      },
      "status": "closed",
      "timestamps": {
        "opened_at_utc": "2026-04-30T13:27:47.379051+00:00",
        "dashboard_timestamp_utc": "2026-04-30T13:03:40Z",
        "updated_at_utc": null,
        "closed_at_utc": "2026-05-09T07:52:47.339302+00:00"
      },
      "fill_source": "copilot_virtual_portfolio_json",
      "exit_reason": "closed_in_paper_ledger",
      "simulated": true,
      "real_order": false,
      "notes": "Opened automatically by active paper-trading rules on watchlist_candidate.",
      "exit_price": 362.75,
      "realized_pnl": 36.45
    },
    {
      "trade_id": "d891939d3881a3fe",
      "symbol": "BTC",
      "side": "long",
      "setup_source": "copilot_filtered_decision",
      "entry": 80354.0,
      "size": {
        "quantity": 0.01495918,
        "notional_usd": 1202.03,
        "risk_fraction": 0.01,
        "risk_note": "Paper sizing placeholder; no real capital committed."
      },
      "targets": [
        {
          "label": "tp1",
          "price": 80444.183594
        },
        {
          "label": "tp2",
          "price": 80475.34375
        }
      ],
      "invalidation": {
        "price": 80354.0,
        "reason": "Paper stop/invalidation from source decision."
      },
      "status": "closed",
      "timestamps": {
        "opened_at_utc": "2026-05-09T08:08:22.403063+00:00",
        "dashboard_timestamp_utc": "2026-05-09T08:05:21Z",
        "updated_at_utc": null,
        "closed_at_utc": "2026-05-09T09:33:06.063422+00:00"
      },
      "fill_source": "local_paper_simulator",
      "exit_reason": "closed_in_paper_ledger",
      "simulated": true,
      "real_order": false,
      "notes": "Opened automatically by active paper-trading rules on approved_candidate.",
      "exit_price": 80354.0,
      "realized_pnl": 0.0
    },
    {
      "trade_id": "2af108e72dd707f0",
      "symbol": "BTC",
      "side": "long",
      "setup_source": "copilot_filtered_decision",
      "entry": 80354.0,
      "size": {
        "quantity": 0.01316412,
        "notional_usd": 1057.79,
        "risk_fraction": 0.01,
        "risk_note": "Paper sizing placeholder; no real capital committed."
      },
      "targets": [
        {
          "label": "tp1",
          "price": 80423.820312
        },
        {
          "label": "tp2",
          "price": 80475.34375
        }
      ],
      "invalidation": {
        "price": 80354.0,
        "reason": "Paper stop/invalidation from source decision."
      },
      "status": "closed",
      "timestamps": {
        "opened_at_utc": "2026-05-09T13:32:59.981383+00:00",
        "dashboard_timestamp_utc": "2026-05-09T13:31:22Z",
        "updated_at_utc": null,
        "closed_at_utc": "2026-05-09T14:29:33.429919+00:00"
      },
      "fill_source": "local_paper_simulator",
      "exit_reason": "closed_in_paper_ledger",
      "simulated": true,
      "real_order": false,
      "notes": "Opened automatically by active paper-trading rules on approved_candidate.",
      "exit_price": 80354.0,
      "realized_pnl": 0.0
    },
    {
      "trade_id": "c7e222b3a29aaf44",
      "symbol": "ETH",
      "side": "long",
      "setup_source": "copilot_filtered_decision",
      "entry": 2310.420044,
      "size": {
        "quantity": 0.35454592,
        "notional_usd": 819.15,
        "risk_fraction": 0.01,
        "risk_note": "Paper sizing placeholder; no real capital committed."
      },
      "targets": [
        {
          "label": "tp1",
          "price": 2319.23999
        },
        {
          "label": "tp2",
          "price": 2321.43994140625
        }
      ],
      "invalidation": {
        "price": 2310.420044,
        "reason": "Paper stop/invalidation from source decision."
      },
      "status": "closed",
      "timestamps": {
        "opened_at_utc": "2026-05-09T13:48:03.749760+00:00",
        "dashboard_timestamp_utc": "2026-05-09T13:46:23Z",
        "updated_at_utc": null,
        "closed_at_utc": "2026-05-09T14:29:33.430244+00:00"
      },
      "fill_source": "local_paper_simulator",
      "exit_reason": "closed_in_paper_ledger",
      "simulated": true,
      "real_order": false,
      "notes": "Opened automatically by active paper-trading rules on approved_candidate.",
      "exit_price": 2310.420044,
      "realized_pnl": 0.0
    },
    {
      "trade_id": "a47ef47b91b8a321",
      "symbol": "SOL",
      "side": "long",
      "setup_source": "copilot_filtered_decision",
      "entry": 92.77999877929688,
      "size": {
        "quantity": 12.95570183,
        "notional_usd": 1202.03,
        "risk_fraction": 0.01,
        "risk_note": "Paper sizing placeholder; no real capital committed."
      },
      "targets": [
        {
          "label": "tp1",
          "price": 94.16000366210938
        },
        {
          "label": "tp2",
          "price": 94.16000366210938
        }
      ],
      "invalidation": {
        "price": 92.77999877929688,
        "reason": "Paper stop/invalidation from source decision."
      },
      "status": "closed",
      "timestamps": {
        "opened_at_utc": "2026-05-09T09:33:06.064507+00:00",
        "dashboard_timestamp_utc": "2026-05-09T09:31:25Z",
        "updated_at_utc": null,
        "closed_at_utc": "2026-05-09T15:25:18.018738+00:00"
      },
      "fill_source": "local_paper_simulator",
      "exit_reason": "closed_in_paper_ledger",
      "simulated": true,
      "real_order": false,
      "notes": "Opened automatically by active paper-trading rules on approved_candidate.",
      "exit_price": 92.77999877929688,
      "realized_pnl": 0.0
    },
    {
      "trade_id": "edf4bd8d24e457b0",
      "symbol": "SOL",
      "side": "long",
      "setup_source": "copilot_filtered_decision",
      "entry": 92.77999877929688,
      "size": {
        "quantity": 10.34156082,
        "notional_usd": 959.49,
        "risk_fraction": 0.01,
        "risk_note": "Paper sizing placeholder; no real capital committed."
      },
      "targets": [
        {
          "label": "tp1",
          "price": 93.785
        },
        {
          "label": "tp2",
          "price": 94.16000366210938
        }
      ],
      "invalidation": {
        "price": 92.77999877929688,
        "reason": "Paper stop/invalidation from source decision."
      },
      "status": "closed",
      "timestamps": {
        "opened_at_utc": "2026-05-09T15:44:01.778625+00:00",
        "dashboard_timestamp_utc": "2026-05-09T15:31:23Z",
        "updated_at_utc": null,
        "closed_at_utc": "2026-05-09T15:52:06.319254+00:00"
      },
      "fill_source": "local_paper_simulator",
      "exit_reason": "closed_in_paper_ledger",
      "simulated": true,
      "real_order": false,
      "notes": "Opened automatically by active paper-trading rules on approved_candidate.",
      "exit_price": 92.77999877929688,
      "realized_pnl": 0.0
    },
    {
      "trade_id": "f94a5ee4773f55fd",
      "symbol": "ETH",
      "side": "long",
      "setup_source": "copilot_filtered_decision",
      "entry": 2310.420044,
      "size": {
        "quantity": 0.47191852,
        "notional_usd": 1090.33,
        "risk_fraction": 0.01,
        "risk_note": "Paper sizing placeholder; no real capital committed."
      },
      "targets": [
        {
          "label": "tp1",
          "price": 2318.329956
        },
        {
          "label": "tp2",
          "price": 2321.43994140625
        }
      ],
      "invalidation": {
        "price": 2310.420044,
        "reason": "Paper stop/invalidation from source decision."
      },
      "status": "closed",
      "timestamps": {
        "opened_at_utc": "2026-05-09T15:44:01.778128+00:00",
        "dashboard_timestamp_utc": "2026-05-09T15:31:23Z",
        "updated_at_utc": null,
        "closed_at_utc": "2026-05-09T16:22:06.212548+00:00"
      },
      "fill_source": "local_paper_simulator",
      "exit_reason": "closed_in_paper_ledger",
      "simulated": true,
      "real_order": false,
      "notes": "Opened automatically by active paper-trading rules on approved_candidate.",
      "exit_price": 2321.43994140625,
      "realized_pnl": 5.2
    },
    {
      "trade_id": "d91153b7265bb243",
      "symbol": "BTC",
      "side": "long",
      "setup_source": "copilot_filtered_decision",
      "entry": 80475.34375,
      "size": {
        "quantity": 0.01192278,
        "notional_usd": 959.49,
        "risk_fraction": 0.01,
        "risk_note": "Paper sizing placeholder; no real capital committed."
      },
      "targets": [
        {
          "label": "tp1",
          "price": 80647.1015625
        },
        {
          "label": "tp2",
          "price": 80647.1015625
        }
      ],
      "invalidation": {
        "price": 80475.34375,
        "reason": "Paper stop/invalidation from source decision."
      },
      "status": "closed",
      "timestamps": {
        "opened_at_utc": "2026-05-09T15:52:06.319738+00:00",
        "dashboard_timestamp_utc": "2026-05-09T15:46:22Z",
        "updated_at_utc": null,
        "closed_at_utc": "2026-05-09T17:07:43.578048+00:00"
      },
      "fill_source": "local_paper_simulator",
      "exit_reason": "closed_in_paper_ledger",
      "simulated": true,
      "real_order": false,
      "notes": "Opened automatically by active paper-trading rules on approved_candidate.",
      "exit_price": 80647.1015625,
      "realized_pnl": 2.05
    },
    {
      "trade_id": "5c9c94e3573d7d11",
      "symbol": "SOL",
      "side": "short",
      "setup_source": "copilot_filtered_decision",
      "entry": 93.5,
      "size": {
        "quantity": 11.67058824,
        "notional_usd": 1091.2,
        "risk_fraction": 0.01,
        "risk_note": "Paper sizing placeholder; no real capital committed."
      },
      "targets": [
        {
          "label": "tp1",
          "price": 93.110001
        },
        {
          "label": "tp2",
          "price": 92.5999984741211
        }
      ],
      "invalidation": {
        "price": 93.57,
        "reason": "Paper stop/invalidation from source decision."
      },
      "status": "closed",
      "timestamps": {
        "opened_at_utc": "2026-05-10T07:07:54.251887+00:00",
        "dashboard_timestamp_utc": "2026-05-10T07:05:18Z",
        "updated_at_utc": null,
        "closed_at_utc": "2026-05-10T08:25:15.940181+00:00"
      },
      "fill_source": "local_paper_simulator",
      "exit_reason": "closed_in_paper_ledger",
      "simulated": true,
      "real_order": false,
      "notes": "Opened automatically by active paper-trading rules on approved_candidate.",
      "exit_price": 93.57,
      "realized_pnl": -0.82
    },
    {
      "trade_id": "91d673ff33dde6b2",
      "symbol": "ETH",
      "side": "long",
      "setup_source": "copilot_filtered_decision",
      "entry": 2333.36499,
      "size": {
        "quantity": 0.41149585,
        "notional_usd": 960.17,
        "risk_fraction": 0.01,
        "risk_note": "Paper sizing placeholder; no real capital committed."
      },
      "targets": [
        {
          "label": "tp1",
          "price": 2337.449951171875
        },
        {
          "label": "tp2",
          "price": 2337.449951171875
        }
      ],
      "invalidation": {
        "price": 2333.36499,
        "reason": "Paper stop/invalidation from source decision."
      },
      "status": "closed",
      "timestamps": {
        "opened_at_utc": "2026-05-10T15:27:18.617904+00:00",
        "dashboard_timestamp_utc": "2026-05-10T15:21:10Z",
        "updated_at_utc": null,
        "closed_at_utc": "2026-05-10T15:52:51.172668+00:00"
      },
      "fill_source": "local_paper_simulator",
      "exit_reason": "closed_in_paper_ledger",
      "simulated": true,
      "real_order": false,
      "notes": "Opened automatically by active paper-trading rules on approved_candidate.",
      "exit_price": 2337.449951171875,
      "realized_pnl": 1.68
    },
    {
      "trade_id": "fc9f160360e257d8",
      "symbol": "SOL",
      "side": "long",
      "setup_source": "copilot_filtered_decision",
      "entry": 93.785,
      "size": {
        "quantity": 11.63405662,
        "notional_usd": 1091.1,
        "risk_fraction": 0.01,
        "risk_note": "Paper sizing placeholder; no real capital committed."
      },
      "targets": [
        {
          "label": "tp1",
          "price": 94.73999786376953
        },
        {
          "label": "tp2",
          "price": 94.73999786376953
        }
      ],
      "invalidation": {
        "price": 93.785,
        "reason": "Paper stop/invalidation from source decision."
      },
      "status": "closed",
      "timestamps": {
        "opened_at_utc": "2026-05-10T14:57:37.004333+00:00",
        "dashboard_timestamp_utc": "2026-05-10T14:46:22Z",
        "updated_at_utc": null,
        "closed_at_utc": "2026-05-10T16:52:41.782269+00:00"
      },
      "fill_source": "local_paper_simulator",
      "exit_reason": "closed_in_paper_ledger",
      "simulated": true,
      "real_order": false,
      "notes": "Opened automatically by active paper-trading rules on approved_candidate.",
      "exit_price": 94.73999786376953,
      "realized_pnl": 11.11
    },
    {
      "trade_id": "77b210a9765bf574",
      "symbol": "ZEC",
      "side": "long",
      "setup_source": "copilot_filtered_decision",
      "entry": 571.0,
      "size": {
        "quantity": 1.63022767,
        "notional_usd": 930.86,
        "risk_fraction": 0.01,
        "risk_note": "Paper sizing placeholder; no real capital committed."
      },
      "targets": [
        {
          "label": "tp1",
          "price": 625.719970703125
        },
        {
          "label": "tp2",
          "price": 625.719970703125
        }
      ],
      "invalidation": {
        "price": 571.0,
        "reason": "Paper stop/invalidation from source decision."
      },
      "status": "closed",
      "timestamps": {
        "opened_at_utc": "2026-05-09T13:32:59.981935+00:00",
        "dashboard_timestamp_utc": "2026-05-09T13:31:22Z",
        "updated_at_utc": null,
        "closed_at_utc": "2026-05-10T20:52:05.298626+00:00"
      },
      "fill_source": "local_paper_simulator",
      "exit_reason": "closed_in_paper_ledger",
      "simulated": true,
      "real_order": false,
      "notes": "Opened automatically by active paper-trading rules on approved_candidate.",
      "exit_price": 571.0,
      "realized_pnl": 0.0
    }
  ],
  "event_log": [
    {
      "event_id": "76246ec0d3ae5d04",
      "event_type": "ledger_snapshot",
      "created_at_utc": "2026-05-12T08:05:22Z",
      "status": "snapshot_written",
      "simulated": true,
      "real_order": false,
      "fill_source": "none",
      "notes": "Ledger snapshot generated from dashboard action output and optional copilot paper portfolio JSON."
    },
    {
      "event_id": "7844b6d5e94ed20f",
      "event_type": "no_trade_setup",
      "created_at_utc": "2026-05-12T08:05:22Z",
      "symbol": "BTC",
      "side": "long",
      "action_state": "PASS",
      "display_signal": "HOLD",
      "setup_source": "dashboard_action_engine",
      "entry": {
        "low": null,
        "high": null,
        "reference": null
      },
      "targets": [],
      "invalidation": {
        "price": null,
        "reason": "PASS diagnostics: HTF/LTF alignment missing"
      },
      "status": "no_trade",
      "fill_status": "no_trade_no_fill",
      "fill_source": "none",
      "exit_reason": null,
      "current_price": 80863.58,
      "advisory_score": 45,
      "confidence": "LOW",
      "provenance": {
        "source_name": "Binance Spot Public",
        "source": "binance-spot-public",
        "primary": true,
        "public_endpoint_only": true,
        "private_credentials_used": false,
        "real_order": false,
        "symbol": "BTC",
        "symbol_pair": "BTCUSDT",
        "market_type": "spot",
        "endpoint": "/api/v3/ticker/24hr + /api/v3/klines",
        "method": "GET",
        "interval": "1h",
        "limit": 120,
        "data_timestamp_utc": "2026-05-12T08:05:23Z",
        "fetched_at_utc": "2026-05-12T08:05:23Z",
        "fallback_reason": null
      },
      "simulated": true,
      "real_order": false,
      "notes": "Watch-only and dashboard-generated candidates are not exchange fills; this ledger is simulation only."
    },
    {
      "event_id": "d37f7a2bb85dc94d",
      "event_type": "watch_only_setup",
      "created_at_utc": "2026-05-12T08:05:22Z",
      "symbol": "ETH",
      "side": "short",
      "action_state": "WATCHLIST",
      "display_signal": "HOLD",
      "setup_source": "dashboard_action_engine",
      "entry": {
        "low": 2289.219970703125,
        "high": 2296.110107421875,
        "reference": 2292.66503906
      },
      "targets": [],
      "invalidation": {
        "price": 2296.110107421875,
        "reason": "Template invalidation for session-expansion"
      },
      "status": "watch_no_fill",
      "fill_status": "watch_only_no_fill",
      "fill_source": "none",
      "exit_reason": null,
      "current_price": 2290.38,
      "advisory_score": 100,
      "confidence": "VERY_HIGH",
      "provenance": {
        "source_name": "Binance Spot Public",
        "source": "binance-spot-public",
        "primary": true,
        "public_endpoint_only": true,
        "private_credentials_used": false,
        "real_order": false,
        "symbol": "ETH",
        "symbol_pair": "ETHUSDT",
        "market_type": "spot",
        "endpoint": "/api/v3/ticker/24hr + /api/v3/klines",
        "method": "GET",
        "interval": "1h",
        "limit": 120,
        "data_timestamp_utc": "2026-05-12T08:05:23Z",
        "fetched_at_utc": "2026-05-12T08:05:24Z",
        "fallback_reason": null
      },
      "simulated": true,
      "real_order": false,
      "notes": "Watch-only and dashboard-generated candidates are not exchange fills; this ledger is simulation only."
    },
    {
      "event_id": "d0796cdb4310a660",
      "event_type": "watch_only_setup",
      "created_at_utc": "2026-05-12T08:05:22Z",
      "symbol": "SOL",
      "side": "long",
      "action_state": "WATCHLIST",
      "display_signal": "HOLD",
      "setup_source": "dashboard_action_engine",
      "entry": {
        "low": 95.55999755859375,
        "high": 95.72000122070312,
        "reference": 95.63999939
      },
      "targets": [
        {
          "label": "tp1",
          "price": 96.860001
        },
        {
          "label": "tp2",
          "price": 98.37000274658203
        }
      ],
      "invalidation": {
        "price": 95.55999755859375,
        "reason": "Template invalidation for session-expansion"
      },
      "status": "watch_no_fill",
      "fill_status": "watch_only_no_fill",
      "fill_source": "none",
      "exit_reason": null,
      "current_price": 95.8,
      "advisory_score": 100,
      "confidence": "VERY_HIGH",
      "provenance": {
        "source_name": "Binance Spot Public",
        "source": "binance-spot-public",
        "primary": true,
        "public_endpoint_only": true,
        "private_credentials_used": false,
        "real_order": false,
        "symbol": "SOL",
        "symbol_pair": "SOLUSDT",
        "market_type": "spot",
        "endpoint": "/api/v3/ticker/24hr + /api/v3/klines",
        "method": "GET",
        "interval": "1h",
        "limit": 120,
        "data_timestamp_utc": "2026-05-12T08:05:23Z",
        "fetched_at_utc": "2026-05-12T08:05:24Z",
        "fallback_reason": null
      },
      "simulated": true,
      "real_order": false,
      "notes": "Watch-only and dashboard-generated candidates are not exchange fills; this ledger is simulation only."
    },
    {
      "event_id": "ba60d9593abf4282",
      "event_type": "watch_only_setup",
      "created_at_utc": "2026-05-12T08:05:22Z",
      "symbol": "ZEC",
      "side": "short",
      "action_state": "WATCHLIST",
      "display_signal": "HOLD",
      "setup_source": "dashboard_action_engine",
      "entry": {
        "low": 561.1900024414062,
        "high": 566.5800170898438,
        "reference": 563.88500977
      },
      "targets": [
        {
          "label": "tp1",
          "price": 548.780029296875
        },
        {
          "label": "tp2",
          "price": 548.780029296875
        }
      ],
      "invalidation": {
        "price": 566.5800170898438,
        "reason": "Template invalidation for session-expansion"
      },
      "status": "watch_no_fill",
      "fill_status": "watch_only_no_fill",
      "fill_source": "none",
      "exit_reason": null,
      "current_price": 561.2,
      "advisory_score": 99,
      "confidence": "VERY_HIGH",
      "provenance": {
        "source_name": "Binance Spot Public",
        "source": "binance-spot-public",
        "primary": true,
        "public_endpoint_only": true,
        "private_credentials_used": false,
        "real_order": false,
        "symbol": "ZEC",
        "symbol_pair": "ZECUSDT",
        "market_type": "spot",
        "endpoint": "/api/v3/ticker/24hr + /api/v3/klines",
        "method": "GET",
        "interval": "1h",
        "limit": 120,
        "data_timestamp_utc": "2026-05-12T08:05:23Z",
        "fetched_at_utc": "2026-05-12T08:05:25Z",
        "fallback_reason": null
      },
      "simulated": true,
      "real_order": false,
      "notes": "Watch-only and dashboard-generated candidates are not exchange fills; this ledger is simulation only."
    },
    {
      "event_id": "d62a0601089f20d7",
      "event_type": "no_trade_setup",
      "created_at_utc": "2026-05-12T08:05:22Z",
      "symbol": "HYPE",
      "side": null,
      "action_state": "PASS",
      "display_signal": "HOLD",
      "setup_source": "dashboard_action_engine",
      "entry": {
        "low": null,
        "high": null,
        "reference": null
      },
      "targets": [],
      "invalidation": {
        "price": null,
        "reason": null
      },
      "status": "no_trade",
      "fill_status": "no_trade_no_fill",
      "fill_source": "none",
      "exit_reason": null,
      "current_price": 41.273,
      "advisory_score": 15,
      "confidence": "LOW",
      "provenance": {
        "source_name": "Binance USD-M Futures Public",
        "source": "binance-usdm-futures-public",
        "primary": false,
        "public_endpoint_only": true,
        "private_credentials_used": false,
        "real_order": false,
        "symbol": "HYPE",
        "symbol_pair": "HYPEUSDT",
        "market_type": "usd_m_futures",
        "endpoint": "/fapi/v1/ticker/24hr + /fapi/v1/klines",
        "method": "GET",
        "interval": "1h",
        "limit": 120,
        "data_timestamp_utc": "2026-05-12T08:05:23Z",
        "fetched_at_utc": "2026-05-12T08:05:26Z",
        "fallback_reason": "Binance spot unavailable/unsupported (spot HYPEUSDT: HTTP 400: {\"code\":-1121,\"msg\":\"Invalid symbol.\"}); used Binance public USD-M futures market data."
      },
      "simulated": true,
      "real_order": false,
      "notes": "Watch-only and dashboard-generated candidates are not exchange fills; this ledger is simulation only."
    },
    {
      "event_id": "deb13ea38b830b6c",
      "event_type": "no_trade_setup",
      "created_at_utc": "2026-05-12T08:05:22Z",
      "symbol": "ASTER",
      "side": null,
      "action_state": "PASS",
      "display_signal": "HOLD",
      "setup_source": "dashboard_action_engine",
      "entry": {
        "low": null,
        "high": null,
        "reference": null
      },
      "targets": [],
      "invalidation": {
        "price": null,
        "reason": null
      },
      "status": "no_trade",
      "fill_status": "no_trade_no_fill",
      "fill_source": "none",
      "exit_reason": null,
      "current_price": 0.685,
      "advisory_score": 13,
      "confidence": "LOW",
      "provenance": {
        "source_name": "Binance Spot Public",
        "source": "binance-spot-public",
        "primary": true,
        "public_endpoint_only": true,
        "private_credentials_used": false,
        "real_order": false,
        "symbol": "ASTER",
        "symbol_pair": "ASTERUSDT",
        "market_type": "spot",
        "endpoint": "/api/v3/ticker/24hr + /api/v3/klines",
        "method": "GET",
        "interval": "1h",
        "limit": 120,
        "data_timestamp_utc": "2026-05-12T08:05:26Z",
        "fetched_at_utc": "2026-05-12T08:05:27Z",
        "fallback_reason": null
      },
      "simulated": true,
      "real_order": false,
      "notes": "Watch-only and dashboard-generated candidates are not exchange fills; this ledger is simulation only."
    },
    {
      "event_id": "e69503ef70b3054f",
      "event_type": "no_trade_setup",
      "created_at_utc": "2026-05-12T08:05:22Z",
      "symbol": "SENT",
      "side": null,
      "action_state": "PASS",
      "display_signal": "HOLD",
      "setup_source": "dashboard_action_engine",
      "entry": {
        "low": null,
        "high": null,
        "reference": null
      },
      "targets": [],
      "invalidation": {
        "price": null,
        "reason": null
      },
      "status": "no_trade",
      "fill_status": "no_trade_no_fill",
      "fill_source": "none",
      "exit_reason": null,
      "current_price": 0.01735,
      "advisory_score": 13,
      "confidence": "LOW",
      "provenance": {
        "source_name": "Binance Spot Public",
        "source": "binance-spot-public",
        "primary": true,
        "public_endpoint_only": true,
        "private_credentials_used": false,
        "real_order": false,
        "symbol": "SENT",
        "symbol_pair": "SENTUSDT",
        "market_type": "spot",
        "endpoint": "/api/v3/ticker/24hr + /api/v3/klines",
        "method": "GET",
        "interval": "1h",
        "limit": 120,
        "data_timestamp_utc": "2026-05-12T08:05:24Z",
        "fetched_at_utc": "2026-05-12T08:05:26Z",
        "fallback_reason": null
      },
      "simulated": true,
      "real_order": false,
      "notes": "Watch-only and dashboard-generated candidates are not exchange fills; this ledger is simulation only."
    },
    {
      "event_id": "ac3f7789ad094923",
      "event_type": "context_signal",
      "created_at_utc": "2026-05-12T08:05:22Z",
      "symbol": "GOLD",
      "side": "long",
      "action_state": "CONTEXT_ONLY",
      "display_signal": "HOLD",
      "setup_source": "dashboard_action_engine",
      "entry": {
        "low": null,
        "high": null,
        "reference": null
      },
      "targets": [],
      "invalidation": {
        "price": null,
        "reason": "Context asset only"
      },
      "status": "context_only",
      "fill_status": "no_fill_context_only",
      "fill_source": "none",
      "exit_reason": null,
      "current_price": 4710.2001953125,
      "advisory_score": 55,
      "confidence": "MEDIUM",
      "provenance": {
        "source_name": "yfinance-macro",
        "source": "yfinance-macro",
        "primary": false,
        "public_endpoint_only": true,
        "private_credentials_used": false,
        "real_order": false,
        "symbol": "GOLD",
        "symbol_pair": "GC=F",
        "market_type": "macro_context",
        "endpoint": "yfinance.Ticker.history",
        "method": "python-library",
        "interval": "1h",
        "limit": 240,
        "data_timestamp_utc": "2026-05-12T03:00:00-04:00",
        "fetched_at_utc": "2026-05-12T08:05:27Z",
        "fallback_reason": null
      },
      "simulated": true,
      "real_order": false,
      "notes": "Watch-only and dashboard-generated candidates are not exchange fills; this ledger is simulation only."
    },
    {
      "event_id": "b29750980ab1c19f",
      "event_type": "context_signal",
      "created_at_utc": "2026-05-12T08:05:22Z",
      "symbol": "SILVER",
      "side": "long",
      "action_state": "CONTEXT_ONLY",
      "display_signal": "HOLD",
      "setup_source": "dashboard_action_engine",
      "entry": {
        "low": null,
        "high": null,
        "reference": null
      },
      "targets": [],
      "invalidation": {
        "price": null,
        "reason": "Context asset only"
      },
      "status": "context_only",
      "fill_status": "no_fill_context_only",
      "fill_source": "none",
      "exit_reason": null,
      "current_price": 85.23500061035156,
      "advisory_score": 55,
      "confidence": "MEDIUM",
      "provenance": {
        "source_name": "yfinance-macro",
        "source": "yfinance-macro",
        "primary": false,
        "public_endpoint_only": true,
        "private_credentials_used": false,
        "real_order": false,
        "symbol": "SILVER",
        "symbol_pair": "SI=F",
        "market_type": "macro_context",
        "endpoint": "yfinance.Ticker.history",
        "method": "python-library",
        "interval": "1h",
        "limit": 240,
        "data_timestamp_utc": "2026-05-12T03:00:00-04:00",
        "fetched_at_utc": "2026-05-12T08:05:27Z",
        "fallback_reason": null
      },
      "simulated": true,
      "real_order": false,
      "notes": "Watch-only and dashboard-generated candidates are not exchange fills; this ledger is simulation only."
    },
    {
      "event_id": "9decfaee76dda68a",
      "event_type": "context_signal",
      "created_at_utc": "2026-05-12T08:05:22Z",
      "symbol": "CRUDE",
      "side": "long",
      "action_state": "CONTEXT_ONLY",
      "display_signal": "HOLD",
      "setup_source": "dashboard_action_engine",
      "entry": {
        "low": null,
        "high": null,
        "reference": null
      },
      "targets": [],
      "invalidation": {
        "price": null,
        "reason": "Context asset only"
      },
      "status": "context_only",
      "fill_status": "no_fill_context_only",
      "fill_source": "none",
      "exit_reason": null,
      "current_price": 100.55999755859375,
      "advisory_score": 55,
      "confidence": "MEDIUM",
      "provenance": {
        "source_name": "yfinance-macro",
        "source": "yfinance-macro",
        "primary": false,
        "public_endpoint_only": true,
        "private_credentials_used": false,
        "real_order": false,
        "symbol": "CRUDE",
        "symbol_pair": "CL=F",
        "market_type": "macro_context",
        "endpoint": "yfinance.Ticker.history",
        "method": "python-library",
        "interval": "1h",
        "limit": 240,
        "data_timestamp_utc": "2026-05-12T03:00:00-04:00",
        "fetched_at_utc": "2026-05-12T08:05:27Z",
        "fallback_reason": null
      },
      "simulated": true,
      "real_order": false,
      "notes": "Watch-only and dashboard-generated candidates are not exchange fills; this ledger is simulation only."
    },
    {
      "event_id": "b3e235bf3f567782",
      "event_type": "context_signal",
      "created_at_utc": "2026-05-12T08:05:22Z",
      "symbol": "SPX",
      "side": "long",
      "action_state": "CONTEXT_ONLY",
      "display_signal": "HOLD",
      "setup_source": "dashboard_action_engine",
      "entry": {
        "low": null,
        "high": null,
        "reference": null
      },
      "targets": [],
      "invalidation": {
        "price": null,
        "reason": "Context asset only"
      },
      "status": "context_only",
      "fill_status": "no_fill_context_only",
      "fill_source": "none",
      "exit_reason": null,
      "current_price": 7412.9501953125,
      "advisory_score": 55,
      "confidence": "MEDIUM",
      "provenance": {
        "source_name": "yfinance-macro",
        "source": "yfinance-macro",
        "primary": false,
        "public_endpoint_only": true,
        "private_credentials_used": false,
        "real_order": false,
        "symbol": "SPX",
        "symbol_pair": "^GSPC",
        "market_type": "macro_context",
        "endpoint": "yfinance.Ticker.history",
        "method": "python-library",
        "interval": "1h",
        "limit": 240,
        "data_timestamp_utc": "2026-05-11T15:30:00-04:00",
        "fetched_at_utc": "2026-05-12T08:05:27Z",
        "fallback_reason": null
      },
      "simulated": true,
      "real_order": false,
      "notes": "Watch-only and dashboard-generated candidates are not exchange fills; this ledger is simulation only."
    },
    {
      "event_id": "9e22304ed2abf759",
      "event_type": "context_signal",
      "created_at_utc": "2026-05-12T08:05:22Z",
      "symbol": "NDX",
      "side": "long",
      "action_state": "CONTEXT_ONLY",
      "display_signal": "HOLD",
      "setup_source": "dashboard_action_engine",
      "entry": {
        "low": null,
        "high": null,
        "reference": null
      },
      "targets": [],
      "invalidation": {
        "price": null,
        "reason": "Context asset only"
      },
      "status": "context_only",
      "fill_status": "no_fill_context_only",
      "fill_source": "none",
      "exit_reason": null,
      "current_price": 26272.955078125,
      "advisory_score": 55,
      "confidence": "MEDIUM",
      "provenance": {
        "source_name": "yfinance-macro",
        "source": "yfinance-macro",
        "primary": false,
        "public_endpoint_only": true,
        "private_credentials_used": false,
        "real_order": false,
        "symbol": "NDX",
        "symbol_pair": "^IXIC",
        "market_type": "macro_context",
        "endpoint": "yfinance.Ticker.history",
        "method": "python-library",
        "interval": "1h",
        "limit": 240,
        "data_timestamp_utc": "2026-05-11T15:30:00-04:00",
        "fetched_at_utc": "2026-05-12T08:05:27Z",
        "fallback_reason": null
      },
      "simulated": true,
      "real_order": false,
      "notes": "Watch-only and dashboard-generated candidates are not exchange fills; this ledger is simulation only."
    },
    {
      "event_id": "c35cbece78a4b70c",
      "event_type": "context_signal",
      "created_at_utc": "2026-05-12T08:05:22Z",
      "symbol": "DJI",
      "side": "short",
      "action_state": "CONTEXT_ONLY",
      "display_signal": "HOLD",
      "setup_source": "dashboard_action_engine",
      "entry": {
        "low": null,
        "high": null,
        "reference": null
      },
      "targets": [],
      "invalidation": {
        "price": null,
        "reason": "Context asset only"
      },
      "status": "context_only",
      "fill_status": "no_fill_context_only",
      "fill_source": "none",
      "exit_reason": null,
      "current_price": 49707.80859375,
      "advisory_score": 55,
      "confidence": "MEDIUM",
      "provenance": {
        "source_name": "yfinance-macro",
        "source": "yfinance-macro",
        "primary": false,
        "public_endpoint_only": true,
        "private_credentials_used": false,
        "real_order": false,
        "symbol": "DJI",
        "symbol_pair": "^DJI",
        "market_type": "macro_context",
        "endpoint": "yfinance.Ticker.history",
        "method": "python-library",
        "interval": "1h",
        "limit": 240,
        "data_timestamp_utc": "2026-05-11T15:30:00-04:00",
        "fetched_at_utc": "2026-05-12T08:05:27Z",
        "fallback_reason": null
      },
      "simulated": true,
      "real_order": false,
      "notes": "Watch-only and dashboard-generated candidates are not exchange fills; this ledger is simulation only."
    },
    {
      "event_id": "7596dea624ec8b88",
      "event_type": "context_signal",
      "created_at_utc": "2026-05-12T08:05:22Z",
      "symbol": "DXY",
      "side": "long",
      "action_state": "CONTEXT_ONLY",
      "display_signal": "HOLD",
      "setup_source": "dashboard_action_engine",
      "entry": {
        "low": null,
        "high": null,
        "reference": null
      },
      "targets": [],
      "invalidation": {
        "price": null,
        "reason": "Context asset only"
      },
      "status": "context_only",
      "fill_status": "no_fill_context_only",
      "fill_source": "none",
      "exit_reason": null,
      "current_price": 98.26300048828125,
      "advisory_score": 55,
      "confidence": "MEDIUM",
      "provenance": {
        "source_name": "yfinance-macro",
        "source": "yfinance-macro",
        "primary": false,
        "public_endpoint_only": true,
        "private_credentials_used": false,
        "real_order": false,
        "symbol": "DXY",
        "symbol_pair": "DX-Y.NYB",
        "market_type": "macro_context",
        "endpoint": "yfinance.Ticker.history",
        "method": "python-library",
        "interval": "1h",
        "limit": 240,
        "data_timestamp_utc": "2026-05-12T03:00:00-04:00",
        "fetched_at_utc": "2026-05-12T08:05:27Z",
        "fallback_reason": null
      },
      "simulated": true,
      "real_order": false,
      "notes": "Watch-only and dashboard-generated candidates are not exchange fills; this ledger is simulation only."
    },
    {
      "event_id": "e511cd40428a5def",
      "event_type": "context_signal",
      "created_at_utc": "2026-05-12T08:05:22Z",
      "symbol": "VIX",
      "side": "long",
      "action_state": "CONTEXT_ONLY",
      "display_signal": "HOLD",
      "setup_source": "dashboard_action_engine",
      "entry": {
        "low": null,
        "high": null,
        "reference": null
      },
      "targets": [],
      "invalidation": {
        "price": null,
        "reason": "Context asset only"
      },
      "status": "context_only",
      "fill_status": "no_fill_context_only",
      "fill_source": "none",
      "exit_reason": null,
      "current_price": 18.709999084472656,
      "advisory_score": 55,
      "confidence": "MEDIUM",
      "provenance": {
        "source_name": "yfinance-macro",
        "source": "yfinance-macro",
        "primary": false,
        "public_endpoint_only": true,
        "private_credentials_used": false,
        "real_order": false,
        "symbol": "VIX",
        "symbol_pair": "^VIX",
        "market_type": "macro_context",
        "endpoint": "yfinance.Ticker.history",
        "method": "python-library",
        "interval": "1h",
        "limit": 240,
        "data_timestamp_utc": "2026-05-12T02:00:00-05:00",
        "fetched_at_utc": "2026-05-12T08:05:28Z",
        "fallback_reason": null
      },
      "simulated": true,
      "real_order": false,
      "notes": "Watch-only and dashboard-generated candidates are not exchange fills; this ledger is simulation only."
    },
    {
      "event_id": "60fc2c0c60ce5390",
      "event_type": "context_signal",
      "created_at_utc": "2026-05-12T08:05:22Z",
      "symbol": "USD",
      "side": "long",
      "action_state": "CONTEXT_ONLY",
      "display_signal": "HOLD",
      "setup_source": "dashboard_action_engine",
      "entry": {
        "low": null,
        "high": null,
        "reference": null
      },
      "targets": [],
      "invalidation": {
        "price": null,
        "reason": "Context asset only"
      },
      "status": "context_only",
      "fill_status": "no_fill_context_only",
      "fill_source": "none",
      "exit_reason": null,
      "current_price": 98.26300048828125,
      "advisory_score": 55,
      "confidence": "MEDIUM",
      "provenance": {
        "source_name": "yfinance-fx-context",
        "source": "yfinance-fx-context",
        "primary": false,
        "public_endpoint_only": true,
        "private_credentials_used": false,
        "real_order": false,
        "symbol": "USD",
        "symbol_pair": "DX-Y.NYB",
        "market_type": "macro_context",
        "endpoint": "yfinance.Ticker.history",
        "method": "python-library",
        "interval": "1h",
        "limit": 240,
        "data_timestamp_utc": "2026-05-12T03:00:00-04:00",
        "fetched_at_utc": "2026-05-12T08:05:28Z",
        "fallback_reason": null
      },
      "simulated": true,
      "real_order": false,
      "notes": "Watch-only and dashboard-generated candidates are not exchange fills; this ledger is simulation only."
    },
    {
      "event_id": "20d7139cbdf81f52",
      "event_type": "context_signal",
      "created_at_utc": "2026-05-12T08:05:22Z",
      "symbol": "EUR",
      "side": "short",
      "action_state": "CONTEXT_ONLY",
      "display_signal": "HOLD",
      "setup_source": "dashboard_action_engine",
      "entry": {
        "low": null,
        "high": null,
        "reference": null
      },
      "targets": [],
      "invalidation": {
        "price": null,
        "reason": "Context asset only"
      },
      "status": "context_only",
      "fill_status": "no_fill_context_only",
      "fill_source": "none",
      "exit_reason": null,
      "current_price": 1.1749500036239624,
      "advisory_score": 55,
      "confidence": "MEDIUM",
      "provenance": {
        "source_name": "yfinance-fx-context",
        "source": "yfinance-fx-context",
        "primary": false,
        "public_endpoint_only": true,
        "private_credentials_used": false,
        "real_order": false,
        "symbol": "EUR",
        "symbol_pair": "EURUSD=X",
        "market_type": "macro_context",
        "endpoint": "yfinance.Ticker.history",
        "method": "python-library",
        "interval": "1h",
        "limit": 240,
        "data_timestamp_utc": "2026-05-12T09:00:00+01:00",
        "fetched_at_utc": "2026-05-12T08:05:28Z",
        "fallback_reason": null
      },
      "simulated": true,
      "real_order": false,
      "notes": "Watch-only and dashboard-generated candidates are not exchange fills; this ledger is simulation only."
    },
    {
      "event_id": "38b4bbbe49456972",
      "event_type": "context_signal",
      "created_at_utc": "2026-05-12T08:05:22Z",
      "symbol": "TRY",
      "side": "long",
      "action_state": "CONTEXT_ONLY",
      "display_signal": "HOLD",
      "setup_source": "dashboard_action_engine",
      "entry": {
        "low": null,
        "high": null,
        "reference": null
      },
      "targets": [],
      "invalidation": {
        "price": null,
        "reason": "Context asset only"
      },
      "status": "context_only",
      "fill_status": "no_fill_context_only",
      "fill_source": "none",
      "exit_reason": null,
      "current_price": 45.395301818847656,
      "advisory_score": 55,
      "confidence": "MEDIUM",
      "provenance": {
        "source_name": "yfinance-fx-context",
        "source": "yfinance-fx-context",
        "primary": false,
        "public_endpoint_only": true,
        "private_credentials_used": false,
        "real_order": false,
        "symbol": "TRY",
        "symbol_pair": "TRY=X",
        "market_type": "macro_context",
        "endpoint": "yfinance.Ticker.history",
        "method": "python-library",
        "interval": "1h",
        "limit": 240,
        "data_timestamp_utc": "2026-05-12T09:00:00+01:00",
        "fetched_at_utc": "2026-05-12T08:05:28Z",
        "fallback_reason": null
      },
      "simulated": true,
      "real_order": false,
      "notes": "Watch-only and dashboard-generated candidates are not exchange fills; this ledger is simulation only."
    }
  ],
  "limitations": [
    "Uses Binance public market-data endpoints only; no real orders are placed.",
    "Dashboard action-engine events do not auto-fill watch-only setups.",
    "Open positions, when present, are imported from the local copilot paper portfolio JSON and marked simulated.",
    "Execution price, slippage, fees, and exits remain paper-model placeholders unless a dedicated simulator updates them."
  ]
}
